{
    "posts": [
        {
            "Post": {
                "author": "_metamythical",
                "author_flair_css_class": null,
                "author_flair_richtext": [],
                "author_flair_text": null,
                "author_flair_type": "text",
                "can_mod_post": false,
                "contest_mode": false,
                "created_utc": 1524925417,
                "domain": "benjaminstudebaker.com",
                "full_link": "https://www.reddit.com/r/stupidpol/comments/8fk6qk/the_left_is_not_a_church_on_the_easy_bay_dsa/",
                "id": "8fk6qk",
                "is_crosspostable": true,
                "is_original_content": false,
                "is_reddit_media_domain": false,
                "is_self": false,
                "is_video": false,
                "link_flair_richtext": [],
                "link_flair_text_color": "dark",
                "link_flair_type": "text",
                "locked": false,
                "no_follow": true,
                "num_comments": 1,
                "num_crossposts": 0,
                "over_18": false,
                "permalink": "/r/stupidpol/comments/8fk6qk/the_left_is_not_a_church_on_the_easy_bay_dsa/",
                "pinned": false,
                "post_hint": "link",
                "preview": {
                    "enabled": false,
                    "images": [
                        {
                            "id": "lL18BYGlmfNB1NOHy612d878rqj-qsIO2652mg-9rzE",
                            "resolutions": [
                                {
                                    "height": 74,
                                    "url": "https://i.redditmedia.com/rpXhRxV1hQl3tUtGrju2gPNs1RsDs8Sid9o4S8cX4Xo.jpg?fit=crop&amp;crop=faces%2Centropy&amp;arh=2&amp;w=108&amp;s=5ff50ccdcb041ae6e8843204c82b35c9",
                                    "width": 108
                                },
                                {
                                    "height": 148,
                                    "url": "https://i.redditmedia.com/rpXhRxV1hQl3tUtGrju2gPNs1RsDs8Sid9o4S8cX4Xo.jpg?fit=crop&amp;crop=faces%2Centropy&amp;arh=2&amp;w=216&amp;s=0504864dcb90f946d3d520d5b0e360bd",
                                    "width": 216
                                },
                                {
                                    "height": 219,
                                    "url": "https://i.redditmedia.com/rpXhRxV1hQl3tUtGrju2gPNs1RsDs8Sid9o4S8cX4Xo.jpg?fit=crop&amp;crop=faces%2Centropy&amp;arh=2&amp;w=320&amp;s=14f2b940f0d09be4eadfd7546973f160",
                                    "width": 320
                                },
                                {
                                    "height": 439,
                                    "url": "https://i.redditmedia.com/rpXhRxV1hQl3tUtGrju2gPNs1RsDs8Sid9o4S8cX4Xo.jpg?fit=crop&amp;crop=faces%2Centropy&amp;arh=2&amp;w=640&amp;s=98c27cdf70ea4435871562cd48b93048",
                                    "width": 640
                                },
                                {
                                    "height": 659,
                                    "url": "https://i.redditmedia.com/rpXhRxV1hQl3tUtGrju2gPNs1RsDs8Sid9o4S8cX4Xo.jpg?fit=crop&amp;crop=faces%2Centropy&amp;arh=2&amp;w=960&amp;s=2e96bfb278dd94f145663bd43756f224",
                                    "width": 960
                                }
                            ],
                            "source": {
                                "height": 666,
                                "url": "https://i.redditmedia.com/rpXhRxV1hQl3tUtGrju2gPNs1RsDs8Sid9o4S8cX4Xo.jpg?s=badde6f2ea8d235b9eec4a57aeca0b55",
                                "width": 970
                            },
                            "variants": {}
                        }
                    ]
                },
                "retrieved_on": 1524928496,
                "score": 13,
                "selftext": "",
                "send_replies": false,
                "spoiler": false,
                "stickied": false,
                "subreddit": "stupidpol",
                "subreddit_id": "t5_hitz3",
                "subreddit_subscribers": 27,
                "subreddit_type": "public",
                "thumbnail": "https://a.thumbs.redditmedia.com/yW-sFIAAXHZaQ0Q2xeNjl0JteBZ8Wsewoi4vpjBMtT8.jpg",
                "title": "The Left is Not a Church (on the Easy Bay DSA election)",
                "url": "https://benjaminstudebaker.com/2018/04/28/the-left-is-not-a-church/",
                "thumbnail_height": 96,
                "thumbnail_width": 140
            },
            "Comments": [
                {
                    "approved_at_utc": null,
                    "associated_award": null,
                    "author": "CorticoefferentCrab",
                    "author_flair_background_color": null,
                    "author_flair_css_class": null,
                    "author_flair_richtext": [],
                    "author_flair_template_id": null,
                    "author_flair_text": null,
                    "author_flair_text_color": null,
                    "author_flair_type": "text",
                    "banned_at_utc": null,
                    "body": "Excellent article",
                    "can_mod_post": false,
                    "collapsed": false,
                    "collapsed_because_crowd_control": null,
                    "collapsed_reason": null,
                    "created_utc": 1524928770,
                    "distinguished": null,
                    "edited": "false",
                    "id": "dy48et8",
                    "is_submitter": false,
                    "link_id": "t3_8fk6qk",
                    "no_follow": true,
                    "parent_id": "t3_8fk6qk",
                    "permalink": "/r/stupidpol/comments/8fk6qk/the_left_is_not_a_church_on_the_easy_bay_dsa/dy48et8/",
                    "retrieved_on": 1524928771,
                    "score": 1,
                    "send_replies": true,
                    "stickied": false,
                    "subreddit": "stupidpol",
                    "subreddit_id": "t5_hitz3",
                    "top_awarded_type": null
                }
            ]
        },
        {
            "Post": {
                "author": "guccibananabricks",
                "author_flair_css_class": null,
                "author_flair_richtext": [],
                "author_flair_text": null,
                "author_flair_type": "text",
                "can_mod_post": false,
                "contest_mode": false,
                "created_utc": 1524922391,
                "domain": "i.redd.it",
                "full_link": "https://www.reddit.com/r/stupidpol/comments/8fjwjg/the_lengths_some_people_go_to_prove_raceclass/",
                "id": "8fjwjg",
                "is_crosspostable": true,
                "is_original_content": false,
                "is_reddit_media_domain": true,
                "is_self": false,
                "is_video": false,
                "link_flair_richtext": [],
                "link_flair_text_color": "dark",
                "link_flair_type": "text",
                "locked": false,
                "no_follow": true,
                "num_comments": 0,
                "num_crossposts": 0,
                "over_18": false,
                "permalink": "/r/stupidpol/comments/8fjwjg/the_lengths_some_people_go_to_prove_raceclass/",
                "pinned": false,
                "post_hint": "image",
                "preview": {
                    "enabled": true,
                    "images": [
                        {
                            "id": "fZka-NZDLq5rRQc1vDXFVd8YdCNAvKXMMdF6pqfqSrY",
                            "resolutions": [
                                {
                                    "height": 78,
                                    "url": "https://i.redditmedia.com/07yUDWqwkEhig8bEDCfHsF9mdqtWAzXJfKaCYPVlVBQ.png?fit=crop&amp;crop=faces%2Centropy&amp;arh=2&amp;w=108&amp;s=8e67745e5356fec8c7783ff5250d58fa",
                                    "width": 108
                                },
                                {
                                    "height": 156,
                                    "url": "https://i.redditmedia.com/07yUDWqwkEhig8bEDCfHsF9mdqtWAzXJfKaCYPVlVBQ.png?fit=crop&amp;crop=faces%2Centropy&amp;arh=2&amp;w=216&amp;s=06ac937af0294aa61bcbab4118b65da8",
                                    "width": 216
                                },
                                {
                                    "height": 231,
                                    "url": "https://i.redditmedia.com/07yUDWqwkEhig8bEDCfHsF9mdqtWAzXJfKaCYPVlVBQ.png?fit=crop&amp;crop=faces%2Centropy&amp;arh=2&amp;w=320&amp;s=c28af18436deb0a7243a7055ead10d5a",
                                    "width": 320
                                }
                            ],
                            "source": {
                                "height": 335,
                                "url": "https://i.redditmedia.com/07yUDWqwkEhig8bEDCfHsF9mdqtWAzXJfKaCYPVlVBQ.png?s=02a8e8fc9dc25be2d88d7a4e1363967b",
                                "width": 463
                            },
                            "variants": {}
                        }
                    ]
                },
                "retrieved_on": 1524925693,
                "score": 9,
                "selftext": "",
                "send_replies": true,
                "spoiler": false,
                "stickied": false,
                "subreddit": "stupidpol",
                "subreddit_id": "t5_hitz3",
                "subreddit_subscribers": 27,
                "subreddit_type": "public",
                "thumbnail": "https://b.thumbs.redditmedia.com/kYBuyquedEQ0a1OAfGu9yukMmRaxd0hvXW0wv5yIS1g.jpg",
                "title": "The lengths some people go to prove race&gt;class.",
                "url": "https://i.redd.it/nufjyirhjnu01.png",
                "thumbnail_height": 101,
                "thumbnail_width": 140
            },
            "Comments": []
        },
        {
            "Post": {
                "author": "CorticoefferentCrab",
                "author_flair_css_class": null,
                "author_flair_richtext": [],
                "author_flair_text": null,
                "author_flair_type": "text",
                "can_mod_post": false,
                "contest_mode": false,
                "created_utc": 1524885457,
                "domain": "adidasmarxism.wordpress.com",
                "full_link": "https://www.reddit.com/r/stupidpol/comments/8fh9l1/american_thought_idpol_as_intellectual_imperialism/",
                "id": "8fh9l1",
                "is_crosspostable": true,
                "is_original_content": false,
                "is_reddit_media_domain": false,
                "is_self": false,
                "is_video": false,
                "link_flair_richtext": [],
                "link_flair_text_color": "dark",
                "link_flair_type": "text",
                "locked": false,
                "no_follow": true,
                "num_comments": 3,
                "num_crossposts": 0,
                "over_18": false,
                "permalink": "/r/stupidpol/comments/8fh9l1/american_thought_idpol_as_intellectual_imperialism/",
                "pinned": false,
                "post_hint": "link",
                "preview": {
                    "enabled": false,
                    "images": [
                        {
                            "id": "ylBa4JEkDe_YNcK8o9xYUPeCsCTGY-981qIRRRvsGX8",
                            "resolutions": [
                                {
                                    "height": 111,
                                    "url": "https://i.redditmedia.com/6w2wkKFfKGqbamvlE_nLzLVEBnBW94uCDTbeG5JLd_s.jpg?fit=crop&amp;crop=faces%2Centropy&amp;arh=2&amp;w=108&amp;s=10aa2214d4690f6e2df69b980a8d5241",
                                    "width": 108
                                },
                                {
                                    "height": 222,
                                    "url": "https://i.redditmedia.com/6w2wkKFfKGqbamvlE_nLzLVEBnBW94uCDTbeG5JLd_s.jpg?fit=crop&amp;crop=faces%2Centropy&amp;arh=2&amp;w=216&amp;s=672ed4d4e45c1ae15f7555dee5fa6148",
                                    "width": 216
                                },
                                {
                                    "height": 329,
                                    "url": "https://i.redditmedia.com/6w2wkKFfKGqbamvlE_nLzLVEBnBW94uCDTbeG5JLd_s.jpg?fit=crop&amp;crop=faces%2Centropy&amp;arh=2&amp;w=320&amp;s=0aa86e40a63b2a9112204e28550a03b5",
                                    "width": 320
                                },
                                {
                                    "height": 658,
                                    "url": "https://i.redditmedia.com/6w2wkKFfKGqbamvlE_nLzLVEBnBW94uCDTbeG5JLd_s.jpg?fit=crop&amp;crop=faces%2Centropy&amp;arh=2&amp;w=640&amp;s=a750c18fe03bf2a9579184e941a3a583",
                                    "width": 640
                                }
                            ],
                            "source": {
                                "height": 777,
                                "url": "https://i.redditmedia.com/6w2wkKFfKGqbamvlE_nLzLVEBnBW94uCDTbeG5JLd_s.jpg?s=7d80456ef64dc083d18a00d854a79d11",
                                "width": 755
                            },
                            "variants": {}
                        }
                    ]
                },
                "retrieved_on": 1524889063,
                "score": 11,
                "selftext": "",
                "send_replies": true,
                "spoiler": false,
                "stickied": false,
                "subreddit": "stupidpol",
                "subreddit_id": "t5_hitz3",
                "subreddit_subscribers": 27,
                "subreddit_type": "public",
                "thumbnail": "https://b.thumbs.redditmedia.com/-s5ddMVv1NG1EWqktWl2n5YOdfiNy6SbeGXWjyozNAU.jpg",
                "title": "\"American Thought\": idpol as intellectual imperialism",
                "url": "https://adidasmarxism.wordpress.com/2017/08/25/american-thought-from-theoretical-barbarism-to-intellectual-decadence/",
                "thumbnail_height": 140,
                "thumbnail_width": 140
            },
            "Comments": [
                {
                    "approved_at_utc": null,
                    "associated_award": null,
                    "author": "CorticoefferentCrab",
                    "author_flair_background_color": null,
                    "author_flair_css_class": null,
                    "author_flair_richtext": [],
                    "author_flair_template_id": null,
                    "author_flair_text": null,
                    "author_flair_text_color": null,
                    "author_flair_type": "text",
                    "banned_at_utc": null,
                    "body": "&gt; What do I mean when I say \u2018American Thought\u2019? I am talking (mostly) about ideas such as cultural appropriation, identity politics, intersectionality, empowerment, shaming and privilege theories and American theories about race and racism, which the American left is mixing with Marxism, Third World \u201cprogressive\u201d ethno-nationalism and projecting to the rest of the World \u2013 mostly Europe \u2013 without any real materialist analysis to back up these thoughts.",
                    "can_mod_post": false,
                    "collapsed": false,
                    "collapsed_because_crowd_control": null,
                    "collapsed_reason": null,
                    "created_utc": 1524885496,
                    "distinguished": null,
                    "edited": "false",
                    "id": "dy3jnw0",
                    "is_submitter": true,
                    "link_id": "t3_8fh9l1",
                    "no_follow": true,
                    "parent_id": "t3_8fh9l1",
                    "permalink": "/r/stupidpol/comments/8fh9l1/american_thought_idpol_as_intellectual_imperialism/dy3jnw0/",
                    "retrieved_on": 1524885497,
                    "score": 1,
                    "send_replies": true,
                    "stickied": false,
                    "subreddit": "stupidpol",
                    "subreddit_id": "t5_hitz3",
                    "top_awarded_type": null
                },
                {
                    "approved_at_utc": null,
                    "associated_award": null,
                    "author": "AffectionateSwimming",
                    "author_flair_background_color": null,
                    "author_flair_css_class": null,
                    "author_flair_richtext": [],
                    "author_flair_template_id": null,
                    "author_flair_text": null,
                    "author_flair_text_color": null,
                    "author_flair_type": "text",
                    "banned_at_utc": null,
                    "body": "This is extremely good.\n\nMods should add it to the sidebar.",
                    "can_mod_post": false,
                    "collapsed": false,
                    "collapsed_because_crowd_control": null,
                    "collapsed_reason": null,
                    "created_utc": 1525016146,
                    "distinguished": null,
                    "edited": "false",
                    "id": "dy5yzoh",
                    "is_submitter": false,
                    "link_id": "t3_8fh9l1",
                    "no_follow": true,
                    "parent_id": "t3_8fh9l1",
                    "permalink": "/r/stupidpol/comments/8fh9l1/american_thought_idpol_as_intellectual_imperialism/dy5yzoh/",
                    "retrieved_on": 1525016147,
                    "score": 1,
                    "send_replies": true,
                    "stickied": false,
                    "subreddit": "stupidpol",
                    "subreddit_id": "t5_hitz3",
                    "top_awarded_type": null
                },
                {
                    "approved_at_utc": null,
                    "associated_award": null,
                    "author": "CorticoefferentCrab",
                    "author_flair_background_color": null,
                    "author_flair_css_class": null,
                    "author_flair_richtext": [],
                    "author_flair_template_id": null,
                    "author_flair_text": null,
                    "author_flair_text_color": null,
                    "author_flair_type": "text",
                    "banned_at_utc": null,
                    "body": "Added!",
                    "can_mod_post": false,
                    "collapsed": false,
                    "collapsed_because_crowd_control": null,
                    "collapsed_reason": null,
                    "created_utc": 1525021881,
                    "distinguished": null,
                    "edited": "false",
                    "id": "dy64al9",
                    "is_submitter": true,
                    "link_id": "t3_8fh9l1",
                    "no_follow": true,
                    "parent_id": "t1_dy5yzoh",
                    "permalink": "/r/stupidpol/comments/8fh9l1/american_thought_idpol_as_intellectual_imperialism/dy64al9/",
                    "retrieved_on": 1525021882,
                    "score": 1,
                    "send_replies": true,
                    "stickied": false,
                    "subreddit": "stupidpol",
                    "subreddit_id": "t5_hitz3",
                    "top_awarded_type": null
                }
            ]
        }
    ]
}